aegis_model/__init__.py
aegis_model/main/__init__.py
aegis_model/main/run.py
aegis_model/model/__init__.py
aegis_model/model/preprocessor.py
aegis_model/model/winrate_model.py
aegis_model/util/__init__.py
aegis_model/util/ansi_code.py
aegis_model/util/aux_functions.py
aegis_model/util/config.py
aegis_model-0.1.dist-info/LICENSE
aegis_model-0.1.dist-info/METADATA
aegis_model-0.1.dist-info/WHEEL
aegis_model-0.1.dist-info/top_level.txt
aegis_model-0.1.dist-info/RECORD
